certbot_dns_dnsmanager/__init__.py
certbot_dns_dnsmanager/dns_dnsmanager.py
certbot_dns_dnsmanager-1.1.0.dist-info/LICENSE.md
certbot_dns_dnsmanager-1.1.0.dist-info/METADATA
certbot_dns_dnsmanager-1.1.0.dist-info/WHEEL
certbot_dns_dnsmanager-1.1.0.dist-info/entry_points.txt
certbot_dns_dnsmanager-1.1.0.dist-info/top_level.txt
certbot_dns_dnsmanager-1.1.0.dist-info/RECORD
