Metadata-Version: 2.1
Name: certbot-dns-dnsmanager
Version: 1.1.0
Summary: dnsmanager.io DNS Authenticator plugin for Certbot
Home-page: https://github.com/stayallive/certbot-dns-dnsmanager
Author: Alex Bouma
Author-email: alex+certbot-dns-dnsmanager@bouma.me
License: MIT
Classifier: Development Status :: 5 - Production/Stable
Classifier: Environment :: Plugins
Classifier: Intended Audience :: System Administrators
Classifier: License :: OSI Approved :: MIT License
Classifier: Operating System :: POSIX :: Linux
Classifier: Programming Language :: Python
Classifier: Programming Language :: Python :: 3
Classifier: Programming Language :: Python :: 3.6
Classifier: Programming Language :: Python :: 3.7
Classifier: Programming Language :: Python :: 3.8
Classifier: Programming Language :: Python :: 3.9
Classifier: Programming Language :: Python :: 3.10
Classifier: Topic :: Internet :: WWW/HTTP
Classifier: Topic :: Security
Classifier: Topic :: System :: Installation/Setup
Classifier: Topic :: System :: Networking
Classifier: Topic :: System :: Systems Administration
Classifier: Topic :: Utilities
Requires-Python: >=3.6
License-File: LICENSE.md
Requires-Dist: requests>=2.25.1
Requires-Dist: setuptools>=41.6.0
Requires-Dist: acme>=1.1.0
Requires-Dist: certbot>=1.1.0
